cognito_clean/cognito_cleaner.py
cognito_clean/cognito_manager.py
cognito_clean/file_manager.py
cognito_clean/notification_service.py
cognito_clean-0.1.0.dist-info/LICENSE
cognito_clean-0.1.0.dist-info/METADATA
cognito_clean-0.1.0.dist-info/WHEEL
cognito_clean-0.1.0.dist-info/entry_points.txt
cognito_clean-0.1.0.dist-info/RECORD
