Metadata-Version: 2.1
Name: cognito-clean
Version: 0.1.0
Summary: Cleans unconfirmed users from a Cognito User Pool
Home-page: https://github.com/XargsUK/cognito-clean
License: MIT
Keywords: aws,lambda,cognito,clean,unconfirmed
Author: XargsUK
Author-email: 51077147+XargsUK@users.noreply.github.com
Maintainer: XargsUK
Maintainer-email: 51077147+XargsUK@users.noreply.github.com
Requires-Python: >=3.8.1,<4.0.0
Classifier: Development Status :: 4 - Beta
Classifier: Intended Audience :: Developers
Classifier: License :: OSI Approved :: MIT License
Classifier: Operating System :: OS Independent
Classifier: Programming Language :: Python :: 3
Classifier: Programming Language :: Python :: 3.9
Classifier: Programming Language :: Python :: 3.10
Classifier: Programming Language :: Python :: 3.11
Classifier: Programming Language :: Python :: 3.12
Classifier: Programming Language :: Python :: 3.8
Classifier: Topic :: Software Development :: Libraries
Classifier: Topic :: Utilities
Requires-Dist: boto3 (>=1.30,<2.0)
Requires-Dist: pytz (>=2024.1,<2025.0)
Project-URL: Repository, https://github.com/XargsUK/cognito-clean
